{
  "pattern": "minecraft:eye",
  "effects": {
    "vanillaplus:final_incoming_damage_multiplier": [
      {
        "effect": {
          "type": "minecraft:add",
          "value": {
            "type": "vanillaplus:preset",
            "value": "vanillaplus:trim_pattern_effect/eye",
            "name": "damage_reduction"
          }
        },
        "requirements": {
          "condition": "minecraft:entity_properties",
          "entity": "attacker",
          "predicate": {
            "type": "minecraft:enderman"
          }
        }
      }
    ],
    "vanillaplus:post_damage": [
      {
        "effect": {
          "type": "vanillaplus:heal_entity",
          "min_amount": {
            "type": "vanillaplus:preset",
            "value": "vanillaplus:trim_pattern_effect/eye",
            "name": "heal"
          },
          "max_amount": {
            "type": "vanillaplus:preset",
            "value": "vanillaplus:trim_pattern_effect/eye",
            "name": "heal"
          }
        },
        "requirements": {
          "condition": "minecraft:damage_source_properties",
          "predicate": {
            "tags": [
              {
                "expected": true,
                "id": "vanillaplus:is_ender_pearl"
              },
              {
                "expected": false,
                "id": "minecraft:bypasses_invulnerability"
              }
            ]
          }
        }
      }
    ]
  }
}